pytest_in_robotframework/__init__.py
pytest_in_robotframework/pytest_in_robotframework.py
pytest_in_robotframework/pytest_plugin_log_to_robot_framework.py
pytest_in_robotframework-0.0.14.dist-info/METADATA
pytest_in_robotframework-0.0.14.dist-info/WHEEL
pytest_in_robotframework-0.0.14.dist-info/top_level.txt
pytest_in_robotframework-0.0.14.dist-info/RECORD
