Metadata-Version: 2.1
Name: pytest-in-robotframework
Version: 0.0.14
Summary: The extension enables easy execution of pytest tests within the Robot Framework environment.
Author: Petr Kus
Author-email: petrkus@email.cz
Classifier: Programming Language :: Python :: 3
Classifier: License :: OSI Approved :: MIT License
Classifier: Operating System :: OS Independent
Classifier: Framework :: Pytest
Classifier: Framework :: Robot Framework
Classifier: Framework :: Robot Framework :: Library
Classifier: Framework :: Robot Framework :: Tool
Classifier: Topic :: Software Development :: Testing
Classifier: Topic :: Software Development :: Quality Assurance
Requires-Python: >=3.8
Requires-Dist: pytest
Requires-Dist: robotframework>=6.1
Requires-Dist: decorator
Requires-Dist: pytest-is-running
